{
 "absolute_value": 0,
 "align_labels_right": 0,
 "creation": "2025-12-26 11:24:21.933354",
 "custom_format": 0,
 "default_print_language": "en",
 "disabled": 0,
 "doc_type": "Shop Rent Payment",
 "docstatus": 0,
 "doctype": "Print Format",
 "font_size": 14,
 "format_data": "[{\"fieldname\": \"print_heading_template\", \"fieldtype\": \"Custom HTML\", \"options\": \"<div class=\\\"print-heading\\\">\\t\\t\\t\\t<h2><div>Shop Rent Payment</div><br><small class=\\\"sub-heading\\\">{{ _(doc.name) }}</small>\\t\\t\\t\\t</h2></div>\"}, {\"fieldtype\": \"Section Break\", \"label\": \"\"}, {\"fieldtype\": \"Column Break\"}, {\"fieldname\": \"contract\", \"print_hide\": 0, \"label\": \"Contract\"}, {\"fieldname\": \"shop\", \"print_hide\": 0, \"label\": \"Shop\"}, {\"fieldname\": \"tenant\", \"print_hide\": 0, \"label\": \"Tenant\"}, {\"fieldtype\": \"Column Break\"}, {\"fieldname\": \"payment_date\", \"print_hide\": 0, \"label\": \"Payment Date\"}, {\"fieldname\": \"status\", \"print_hide\": 0, \"label\": \"Status\"}, {\"fieldname\": \"rent_amount\", \"print_hide\": 0, \"label\": \"Rent Amount\"}]",
 "idx": 0,
 "line_breaks": 0,
 "margin_bottom": 15.0,
 "margin_left": 15.0,
 "margin_right": 15.0,
 "margin_top": 15.0,
 "modified": "2025-12-26 11:25:23.574977",
 "modified_by": "Administrator",
 "module": "Airport Shop Management",
 "name": "Payment Receipt",
 "owner": "Administrator",
 "page_number": "Hide",
 "pdf_generator": "wkhtmltopdf",
 "print_designer": 0,
 "print_designer_template_app": "print_designer",
 "print_format_builder": 0,
 "print_format_builder_beta": 0,
 "print_format_for": "DocType",
 "print_format_type": "Jinja",
 "raw_printing": 0,
 "show_section_headings": 0,
 "standard": "Yes"
}